{
  "id": 2977,
  "sources": [
    {
      "id": 1564,
      "page_ranges": [
        "IUP,ST,11/A2/75-6,94",
        null
      ],
      "short_ref": {
        "id": 760,
        "name": "IUP,ST"
      },
      "item_url": null,
      "thumbnail": null,
      "bib": "<div class=\"csl-bib-body\" style=\"line-height: 1.35; padding-left: 1em; text-indent:-1em;\">\n  <div class=\"csl-entry\"><i>Irish University Press Series of British Parliamentary Papers: Slave Trade</i>. Shannon, Irish University Press, n.d.</div>\n</div>",
      "manifest_content": null,
      "zotero_group_id": 4708800,
      "zotero_item_id": "E7432857",
      "zotero_grouplibrary_name": "sv-docs",
      "zotero_url": "https://www.zotero.org/groups/sv-docs/items/E7432857",
      "title": "Irish University Press Series of British Parliamentary Papers: Slave Trade",
      "is_british_library": false,
      "last_updated": "2024-11-14T15:27:37.947153Z",
      "human_reviewed": null,
      "has_published_manifest": false,
      "notes": "FULL REF: Great Britain, <i>Irish University Press Series of British Parliamentary Papers: Slave Trade</i>, vols. 1-90 (Shannon, 1969-74).\\DOC TYPE: Published source",
      "order_in_shortref": null,
      "source_type": 4,
      "date": 12152
    },
    {
      "id": 1787,
      "page_ranges": [
        "Meyer-Heiselberg,24",
        null
      ],
      "short_ref": {
        "id": 982,
        "name": "Meyer-Heiselberg"
      },
      "item_url": null,
      "thumbnail": null,
      "bib": "<div class=\"csl-bib-body\" style=\"line-height: 1.35; padding-left: 1em; text-indent:-1em;\">\n  <div class=\"csl-entry\">Meyer-Heiselberg, Richard. <i>Notes from the Liberated African Department in the Archives at Fourah Bay College, Freetown, Sierra Leone</i>. Uppsala, SE: The Scandinavian Institute of African Studies, 1967. http://www.slaveryimages.org/s/slaveryimages/item/4037.</div>\n</div>",
      "manifest_content": null,
      "zotero_group_id": 4708800,
      "zotero_item_id": "SG3NSUX8",
      "zotero_grouplibrary_name": "sv-docs",
      "zotero_url": "https://www.zotero.org/groups/sv-docs/items/SG3NSUX8",
      "title": "Notes from the Liberated African Department in the Archives at Fourah Bay College, Freetown, Sierra Leone",
      "is_british_library": false,
      "last_updated": "2024-11-14T15:27:37.109791Z",
      "human_reviewed": null,
      "has_published_manifest": false,
      "notes": "FULL REF: Meyer-Heiselberg, R., <i>Notes from the Liberated African Department in the Archives at Fourah Bay College, Freetown, Sierra Leone</i> (Uppsala, 1967).\\DOC TYPE: Published source",
      "order_in_shortref": null,
      "source_type": 4,
      "date": 11933
    },
    {
      "id": 1996,
      "page_ranges": [
        "PP,1830,X:126",
        null
      ],
      "short_ref": {
        "id": 1189,
        "name": "PP"
      },
      "item_url": null,
      "thumbnail": null,
      "bib": "<div class=\"csl-bib-body\" style=\"line-height: 1.35; padding-left: 1em; text-indent:-1em;\">\n  <div class=\"csl-entry\"><i>Great Britain, <span style=\"font-style:normal;\">Parliamentary Papers</span>:&#xA0; 1777, Accounts and Papers, No 9 1788, XXII&#xA0; 1789, XXIV, XXV, XXVI 1790, XXIX, XXX, XXXI 1790-91, XXXIV 1792, XXXV 1795-96, XLII&#xA0; 1798-99, XLVIII 1799 XLVIII 1801-2, IV&#xA0; 1803-4, X 1806, XII 1813-14, XII 181</i>, n.d.</div>\n</div>",
      "manifest_content": null,
      "zotero_group_id": 4708800,
      "zotero_item_id": "X6N58B3D",
      "zotero_grouplibrary_name": "sv-docs",
      "zotero_url": "https://www.zotero.org/groups/sv-docs/items/X6N58B3D",
      "title": "Great Britain, <i>Parliamentary Papers</i>:  1777, Accounts and Papers, No 9 1788, XXII  1789, XXIV, XXV, XXVI 1790, XXIX, XXX, XXXI 1790-91, XXXIV 1792, XXXV 1795-96, XLII  1798-99, XLVIII 1799 XLVIII 1801-2, IV  1803-4, X 1806, XII 1813-14, XII 181",
      "is_british_library": false,
      "last_updated": "2024-11-14T15:27:36.309527Z",
      "human_reviewed": null,
      "has_published_manifest": false,
      "notes": "FULL REF: Great Britain, <i>Parliamentary Papers</i>:  1777, Accounts and Papers, No 9 1788, XXII  1789, XXIV, XXV, XXVI 1790, XXIX, XXX, XXXI 1790-91, XXXIV 1792, XXXV 1795-96, XLII  1798-99, XLVIII 1799 XLVIII 1801-2, IV  1803-4, X 1806, XII 1813-14, XII 1816, VII 1823, XIX 1825, XXVII, XXIX  1826, XXIX 1826-7, XXII, XXVI 1828, XXVI 1829, XXVI  1830, X 1831, XIX 1831-32, XLVII 1842, XLIV 1845,XLIX 1847-8, XXII 1852-3, XXXIX\\DOC TYPE: Published source",
      "order_in_shortref": null,
      "source_type": 4,
      "date": 11727
    },
    {
      "id": 2301,
      "page_ranges": [
        "Verger,570",
        null
      ],
      "short_ref": {
        "id": 1489,
        "name": "Verger"
      },
      "item_url": null,
      "thumbnail": null,
      "bib": "<div class=\"csl-bib-body\" style=\"line-height: 1.35; padding-left: 1em; text-indent:-1em;\">\n  <div class=\"csl-entry\">Verger, Pierre. <i>Trade Relations Between the Bight of Benin and Bahia, 17<sup>th</sup> to 19<sup>th</sup> Century&lt;/i&gt;, (Ibadan, 1976).</i>, n.d.</div>\n</div>",
      "manifest_content": null,
      "zotero_group_id": 4708800,
      "zotero_item_id": "WJHHWIIP",
      "zotero_grouplibrary_name": "sv-docs",
      "zotero_url": "https://www.zotero.org/groups/sv-docs/items/WJHHWIIP",
      "title": "Trade Relations Between the Bight of Benin and Bahia, 17<sup>th</sup> to 19<sup>th</sup> Century</i>, (Ibadan, 1976).",
      "is_british_library": false,
      "last_updated": "2024-11-14T15:27:35.161545Z",
      "human_reviewed": null,
      "has_published_manifest": false,
      "notes": "FULL REF: Verger, Pierre, <i>Trade Relations Between the Bight of Benin and Bahia, 17<sup>th</sup> to 19<sup>th</sup> Century</i>, (Ibadan, 1976).\\DOC TYPE: Published source",
      "order_in_shortref": null,
      "source_type": 4,
      "date": 11431
    }
  ],
  "voyage_itinerary": {
    "id": 2885,
    "port_of_departure": {
      "id": 1440,
      "uuid": "3edd28dc-9270-49e7-bf02-f1532984081d",
      "name": "Bahia, place unspecified",
      "longitude": -38.51083,
      "latitude": -12.97111,
      "value": 50299,
      "parent": 91,
      "location_type": 3,
      "spatial_extent": null
    },
    "int_first_port_emb": null,
    "int_second_port_emb": null,
    "int_first_region_purchase_slaves": null,
    "int_second_region_purchase_slaves": null,
    "int_first_port_dis": {
      "id": 1440,
      "uuid": "3edd28dc-9270-49e7-bf02-f1532984081d",
      "name": "Bahia, place unspecified",
      "longitude": -38.51083,
      "latitude": -12.97111,
      "value": 50299,
      "parent": 91,
      "location_type": 3,
      "spatial_extent": null
    },
    "int_second_port_dis": null,
    "int_first_region_slave_landing": {
      "id": 91,
      "uuid": "8ac331e8-3e43-48c8-90fa-cbc8531c7651",
      "name": "Bahia",
      "longitude": -38.516667,
      "latitude": -12.983333,
      "value": 50200,
      "parent": 5,
      "location_type": 2,
      "spatial_extent": null
    },
    "imp_principal_region_slave_dis": {
      "id": 96,
      "uuid": "3d8d483e-4229-4117-a968-abfc5f9f3209",
      "name": "Sierra Leone",
      "longitude": -13.67,
      "latitude": 8.1,
      "value": 60200,
      "parent": 6,
      "location_type": 2,
      "spatial_extent": null
    },
    "int_second_place_region_slave_landing": null,
    "first_place_slave_purchase": {
      "id": 1715,
      "uuid": "350eabc6-fadd-4b49-b8a8-9b529ac7713e",
      "name": "Whydah, Ouidah",
      "longitude": 2.08333,
      "latitude": 6.36667,
      "value": 60515,
      "parent": 99,
      "location_type": 3,
      "spatial_extent": null
    },
    "second_place_slave_purchase": null,
    "third_place_slave_purchase": null,
    "first_region_slave_emb": {
      "id": 99,
      "uuid": "ecae66b8-3656-4480-adc8-472cd3b81ed4",
      "name": "Bight of Benin",
      "longitude": 2.33,
      "latitude": 5.27,
      "value": 60500,
      "parent": 6,
      "location_type": 2,
      "spatial_extent": null
    },
    "second_region_slave_emb": null,
    "third_region_slave_emb": null,
    "port_of_call_before_atl_crossing": null,
    "first_landing_place": {
      "id": 1584,
      "uuid": "833e7c5e-9f72-44c4-af8a-cd0cabbb70da",
      "name": "Freetown",
      "longitude": -13.23,
      "latitude": 8.49,
      "value": 60207,
      "parent": 96,
      "location_type": 3,
      "spatial_extent": null
    },
    "second_landing_place": null,
    "third_landing_place": null,
    "first_landing_region": {
      "id": 96,
      "uuid": "3d8d483e-4229-4117-a968-abfc5f9f3209",
      "name": "Sierra Leone",
      "longitude": -13.67,
      "latitude": 8.1,
      "value": 60200,
      "parent": 6,
      "location_type": 2,
      "spatial_extent": null
    },
    "second_landing_region": null,
    "third_landing_region": null,
    "place_voyage_ended": null,
    "region_of_return": null,
    "broad_region_of_return": null,
    "imp_port_voyage_begin": {
      "id": 1440,
      "uuid": "3edd28dc-9270-49e7-bf02-f1532984081d",
      "name": "Bahia, place unspecified",
      "longitude": -38.51083,
      "latitude": -12.97111,
      "value": 50299,
      "parent": 91,
      "location_type": 3,
      "spatial_extent": null
    },
    "imp_region_voyage_begin": {
      "id": 91,
      "uuid": "8ac331e8-3e43-48c8-90fa-cbc8531c7651",
      "name": "Bahia",
      "longitude": -38.516667,
      "latitude": -12.983333,
      "value": 50200,
      "parent": 5,
      "location_type": 2,
      "spatial_extent": null
    },
    "imp_broad_region_voyage_begin": {
      "id": 5,
      "uuid": "18b02ee5-a63b-4438-bb26-706704d269af",
      "name": "Brazil",
      "longitude": -39.75489,
      "latitude": -18.864582,
      "value": 50000,
      "parent": null,
      "location_type": 1,
      "spatial_extent": null
    },
    "principal_place_of_slave_purchase": {
      "id": 1715,
      "uuid": "350eabc6-fadd-4b49-b8a8-9b529ac7713e",
      "name": "Whydah, Ouidah",
      "longitude": 2.08333,
      "latitude": 6.36667,
      "value": 60515,
      "parent": 99,
      "location_type": 3,
      "spatial_extent": null
    },
    "imp_principal_place_of_slave_purchase": {
      "id": 1715,
      "uuid": "350eabc6-fadd-4b49-b8a8-9b529ac7713e",
      "name": "Whydah, Ouidah",
      "longitude": 2.08333,
      "latitude": 6.36667,
      "value": 60515,
      "parent": 99,
      "location_type": 3,
      "spatial_extent": null
    },
    "imp_principal_region_of_slave_purchase": {
      "id": 99,
      "uuid": "ecae66b8-3656-4480-adc8-472cd3b81ed4",
      "name": "Bight of Benin",
      "longitude": 2.33,
      "latitude": 5.27,
      "value": 60500,
      "parent": 6,
      "location_type": 2,
      "spatial_extent": null
    },
    "imp_broad_region_of_slave_purchase": {
      "id": 6,
      "uuid": "31fbfb92-a521-4d83-a9a4-316ff7f56515",
      "name": "Africa",
      "longitude": 9.343897,
      "latitude": 0.054033,
      "value": 60000,
      "parent": null,
      "location_type": 1,
      "spatial_extent": null
    },
    "principal_port_of_slave_dis": {
      "id": 1584,
      "uuid": "833e7c5e-9f72-44c4-af8a-cd0cabbb70da",
      "name": "Freetown",
      "longitude": -13.23,
      "latitude": 8.49,
      "value": 60207,
      "parent": 96,
      "location_type": 3,
      "spatial_extent": null
    },
    "imp_principal_port_slave_dis": {
      "id": 1584,
      "uuid": "833e7c5e-9f72-44c4-af8a-cd0cabbb70da",
      "name": "Freetown",
      "longitude": -13.23,
      "latitude": 8.49,
      "value": 60207,
      "parent": 96,
      "location_type": 3,
      "spatial_extent": null
    },
    "imp_broad_region_slave_dis": {
      "id": 6,
      "uuid": "31fbfb92-a521-4d83-a9a4-316ff7f56515",
      "name": "Africa",
      "longitude": 9.343897,
      "latitude": 0.054033,
      "value": 60000,
      "parent": null,
      "location_type": 1,
      "spatial_extent": null
    },
    "int_third_port_dis": null,
    "int_fourth_port_dis": null,
    "int_third_place_region_slave_landing": null,
    "int_fourth_place_region_slave_landing": null,
    "ports_called_buying_slaves": null,
    "number_of_ports_of_call": null,
    "voyage": 2977
  },
  "voyage_dates": {
    "id": 2885,
    "voyage_began_sparsedate": {
      "id": 14505,
      "day": 1,
      "month": 7,
      "year": 1826
    },
    "slave_purchase_began_sparsedate": null,
    "vessel_left_port_sparsedate": {
      "id": 14506,
      "day": 4,
      "month": 3,
      "year": 1827
    },
    "first_dis_of_slaves_sparsedate": {
      "id": 14507,
      "day": 15,
      "month": 4,
      "year": 1827
    },
    "date_departed_africa_sparsedate": {
      "id": 14508,
      "day": 4,
      "month": 3,
      "year": 1827
    },
    "arrival_at_second_place_landing_sparsedate": null,
    "third_dis_of_slaves_sparsedate": null,
    "departure_last_place_of_landing_sparsedate": null,
    "voyage_completed_sparsedate": null,
    "imp_voyage_began_sparsedate": {
      "id": 14509,
      "day": null,
      "month": null,
      "year": 1826
    },
    "imp_departed_africa_sparsedate": {
      "id": 14510,
      "day": null,
      "month": null,
      "year": 1827
    },
    "imp_arrival_at_port_of_dis_sparsedate": {
      "id": 14511,
      "day": null,
      "month": null,
      "year": 1827
    },
    "length_middle_passage_days": 42,
    "imp_length_home_to_disembark": 288,
    "imp_length_leaving_africa_to_disembark": 42,
    "voyage": 2977
  },
  "enslavers": [
    {
      "roles": "Captain",
      "enslaver": {
        "id": 1023051,
        "birth_place": null,
        "death_place": null,
        "principal_location": null,
        "principal_alias": "Souza, Joaquim Pinto de",
        "birth_year": null,
        "birth_month": null,
        "birth_day": null,
        "death_year": null,
        "death_month": null,
        "death_day": null,
        "father_name": null,
        "father_occupation": null,
        "mother_name": null,
        "probate_date": null,
        "will_value_pounds": null,
        "will_value_dollars": null,
        "will_court": null,
        "notes": null,
        "is_natural_person": true,
        "last_updated": "2023-11-04T02:36:22.668497Z",
        "number_enslaved_people": null,
        "human_reviewed": false,
        "legacy_id": 1023051
      }
    },
    {
      "roles": "Investor",
      "enslaver": {
        "id": 1023054,
        "birth_place": null,
        "death_place": null,
        "principal_location": null,
        "principal_alias": "M___, V Fernando",
        "birth_year": null,
        "birth_month": null,
        "birth_day": null,
        "death_year": null,
        "death_month": null,
        "death_day": null,
        "father_name": null,
        "father_occupation": null,
        "mother_name": null,
        "probate_date": null,
        "will_value_pounds": null,
        "will_value_dollars": null,
        "will_court": null,
        "notes": null,
        "is_natural_person": true,
        "last_updated": "2023-11-04T02:36:22.738657Z",
        "number_enslaved_people": null,
        "human_reviewed": false,
        "legacy_id": 1023054
      }
    }
  ],
  "named_enslaved_people": [
    {
      "id": 10641,
      "enslaved_id": 10641,
      "documented_name": "Kozee"
    },
    {
      "id": 10642,
      "enslaved_id": 10642,
      "documented_name": "Woosoo"
    },
    {
      "id": 10643,
      "enslaved_id": 10643,
      "documented_name": "Abasee"
    },
    {
      "id": 10644,
      "enslaved_id": 10644,
      "documented_name": "Jedallay"
    },
    {
      "id": 10645,
      "enslaved_id": 10645,
      "documented_name": "Ahtingoe"
    },
    {
      "id": 10646,
      "enslaved_id": 10646,
      "documented_name": "Iozoo"
    },
    {
      "id": 10647,
      "enslaved_id": 10647,
      "documented_name": "Iozoo"
    },
    {
      "id": 10648,
      "enslaved_id": 10648,
      "documented_name": "Bahwoloo"
    },
    {
      "id": 10649,
      "enslaved_id": 10649,
      "documented_name": "Bayong"
    },
    {
      "id": 10650,
      "enslaved_id": 10650,
      "documented_name": "Boyah"
    },
    {
      "id": 10651,
      "enslaved_id": 10651,
      "documented_name": "Appoe"
    },
    {
      "id": 10652,
      "enslaved_id": 10652,
      "documented_name": "Nahwochee"
    },
    {
      "id": 10653,
      "enslaved_id": 10653,
      "documented_name": "Ohoonoo"
    },
    {
      "id": 10654,
      "enslaved_id": 10654,
      "documented_name": "Abattee"
    },
    {
      "id": 10655,
      "enslaved_id": 10655,
      "documented_name": "Dahmalay"
    },
    {
      "id": 10656,
      "enslaved_id": 10656,
      "documented_name": "Ohoonoo"
    },
    {
      "id": 10657,
      "enslaved_id": 10657,
      "documented_name": "Ahdahyah"
    },
    {
      "id": 10658,
      "enslaved_id": 10658,
      "documented_name": "Ahbong"
    },
    {
      "id": 10659,
      "enslaved_id": 10659,
      "documented_name": "Ahfodah"
    },
    {
      "id": 10660,
      "enslaved_id": 10660,
      "documented_name": "Ojoe"
    },
    {
      "id": 10661,
      "enslaved_id": 10661,
      "documented_name": "Ahsoquah"
    },
    {
      "id": 10662,
      "enslaved_id": 10662,
      "documented_name": "Sissoo"
    },
    {
      "id": 10663,
      "enslaved_id": 10663,
      "documented_name": "Sosonah"
    },
    {
      "id": 10664,
      "enslaved_id": 10664,
      "documented_name": "Sah"
    },
    {
      "id": 10665,
      "enslaved_id": 10665,
      "documented_name": "Attoe"
    },
    {
      "id": 10666,
      "enslaved_id": 10666,
      "documented_name": "Tossoo"
    },
    {
      "id": 10667,
      "enslaved_id": 10667,
      "documented_name": "Assah"
    },
    {
      "id": 10668,
      "enslaved_id": 10668,
      "documented_name": "Adowee"
    },
    {
      "id": 10669,
      "enslaved_id": 10669,
      "documented_name": "Awahtangee"
    },
    {
      "id": 10670,
      "enslaved_id": 10670,
      "documented_name": "Ahsobah"
    },
    {
      "id": 10671,
      "enslaved_id": 10671,
      "documented_name": "Gotammay"
    },
    {
      "id": 10672,
      "enslaved_id": 10672,
      "documented_name": "Bosah"
    },
    {
      "id": 10673,
      "enslaved_id": 10673,
      "documented_name": "Sopanway"
    },
    {
      "id": 10674,
      "enslaved_id": 10674,
      "documented_name": "Deganay"
    },
    {
      "id": 10675,
      "enslaved_id": 10675,
      "documented_name": "Kappoo"
    },
    {
      "id": 10676,
      "enslaved_id": 10676,
      "documented_name": "Madawoo"
    },
    {
      "id": 10677,
      "enslaved_id": 10677,
      "documented_name": "Ejoe"
    },
    {
      "id": 10678,
      "enslaved_id": 10678,
      "documented_name": "Gocholoe"
    },
    {
      "id": 10679,
      "enslaved_id": 10679,
      "documented_name": "Bokah"
    },
    {
      "id": 10680,
      "enslaved_id": 10680,
      "documented_name": "Woosoo"
    },
    {
      "id": 10681,
      "enslaved_id": 10681,
      "documented_name": "Bookoo"
    },
    {
      "id": 10682,
      "enslaved_id": 10682,
      "documented_name": "Ahgassanee"
    },
    {
      "id": 10683,
      "enslaved_id": 10683,
      "documented_name": "Ohonah"
    },
    {
      "id": 10684,
      "enslaved_id": 10684,
      "documented_name": "Ezeezoo"
    },
    {
      "id": 10685,
      "enslaved_id": 10685,
      "documented_name": "Allaybah"
    },
    {
      "id": 10686,
      "enslaved_id": 10686,
      "documented_name": "Enah"
    },
    {
      "id": 10687,
      "enslaved_id": 10687,
      "documented_name": "Cubnah"
    },
    {
      "id": 10688,
      "enslaved_id": 10688,
      "documented_name": "Dugwah"
    },
    {
      "id": 10689,
      "enslaved_id": 10689,
      "documented_name": "Tayyah"
    },
    {
      "id": 10690,
      "enslaved_id": 10690,
      "documented_name": "Teah"
    },
    {
      "id": 10691,
      "enslaved_id": 10691,
      "documented_name": "Oboloo"
    },
    {
      "id": 10692,
      "enslaved_id": 10692,
      "documented_name": "Chokolay"
    },
    {
      "id": 10693,
      "enslaved_id": 10693,
      "documented_name": "Pelloo"
    },
    {
      "id": 10694,
      "enslaved_id": 10694,
      "documented_name": "Bosavee"
    },
    {
      "id": 10695,
      "enslaved_id": 10695,
      "documented_name": "Wontamay"
    },
    {
      "id": 10696,
      "enslaved_id": 10696,
      "documented_name": "Iteah"
    },
    {
      "id": 10697,
      "enslaved_id": 10697,
      "documented_name": "Wosavee"
    },
    {
      "id": 10698,
      "enslaved_id": 10698,
      "documented_name": "Esaysoo"
    },
    {
      "id": 10699,
      "enslaved_id": 10699,
      "documented_name": "Dosopay"
    },
    {
      "id": 10700,
      "enslaved_id": 10700,
      "documented_name": "Copay"
    },
    {
      "id": 10701,
      "enslaved_id": 10701,
      "documented_name": "Dosoo"
    },
    {
      "id": 10702,
      "enslaved_id": 10702,
      "documented_name": "Kossoo"
    },
    {
      "id": 10703,
      "enslaved_id": 10703,
      "documented_name": "Ahgussoo"
    },
    {
      "id": 10704,
      "enslaved_id": 10704,
      "documented_name": "Goday"
    },
    {
      "id": 10705,
      "enslaved_id": 10705,
      "documented_name": "Dosahvee"
    },
    {
      "id": 10706,
      "enslaved_id": 10706,
      "documented_name": "Pahgeenoo"
    },
    {
      "id": 10707,
      "enslaved_id": 10707,
      "documented_name": "Sahvee"
    },
    {
      "id": 10708,
      "enslaved_id": 10708,
      "documented_name": "Bayong"
    },
    {
      "id": 10709,
      "enslaved_id": 10709,
      "documented_name": "Ahjahee"
    },
    {
      "id": 10710,
      "enslaved_id": 10710,
      "documented_name": "Ahdalay"
    },
    {
      "id": 10711,
      "enslaved_id": 10711,
      "documented_name": "Woolahtong"
    },
    {
      "id": 10712,
      "enslaved_id": 10712,
      "documented_name": "Lahbatang"
    },
    {
      "id": 10713,
      "enslaved_id": 10713,
      "documented_name": "Bookoo"
    },
    {
      "id": 10714,
      "enslaved_id": 10714,
      "documented_name": "Ahdanganay"
    },
    {
      "id": 10715,
      "enslaved_id": 10715,
      "documented_name": "Sabboo"
    },
    {
      "id": 10716,
      "enslaved_id": 10716,
      "documented_name": "Dadday"
    },
    {
      "id": 10717,
      "enslaved_id": 10717,
      "documented_name": "Boday"
    },
    {
      "id": 10718,
      "enslaved_id": 10718,
      "documented_name": "Bosoo"
    },
    {
      "id": 10719,
      "enslaved_id": 10719,
      "documented_name": "Agonyoo"
    },
    {
      "id": 10720,
      "enslaved_id": 10720,
      "documented_name": "Losoo"
    },
    {
      "id": 10721,
      "enslaved_id": 10721,
      "documented_name": "Ogonoo"
    },
    {
      "id": 10722,
      "enslaved_id": 10722,
      "documented_name": "Azazoo"
    },
    {
      "id": 10723,
      "enslaved_id": 10723,
      "documented_name": "Necorogay"
    },
    {
      "id": 10724,
      "enslaved_id": 10724,
      "documented_name": "Ajash"
    },
    {
      "id": 10725,
      "enslaved_id": 10725,
      "documented_name": "Allahsay"
    },
    {
      "id": 10726,
      "enslaved_id": 10726,
      "documented_name": "Betahvee"
    },
    {
      "id": 10727,
      "enslaved_id": 10727,
      "documented_name": "Ahgodamee"
    },
    {
      "id": 10728,
      "enslaved_id": 10728,
      "documented_name": "Bafah"
    },
    {
      "id": 10729,
      "enslaved_id": 10729,
      "documented_name": "Attackah"
    },
    {
      "id": 10730,
      "enslaved_id": 10730,
      "documented_name": "Guahsoo"
    },
    {
      "id": 10731,
      "enslaved_id": 10731,
      "documented_name": "Dazong"
    },
    {
      "id": 10732,
      "enslaved_id": 10732,
      "documented_name": "Achoo"
    },
    {
      "id": 10733,
      "enslaved_id": 10733,
      "documented_name": "Allozoo"
    },
    {
      "id": 10734,
      "enslaved_id": 10734,
      "documented_name": "Tetay"
    },
    {
      "id": 10735,
      "enslaved_id": 10735,
      "documented_name": "Iomowah"
    },
    {
      "id": 10736,
      "enslaved_id": 10736,
      "documented_name": "Eyoboyong"
    },
    {
      "id": 10737,
      "enslaved_id": 10737,
      "documented_name": "Mahgoo"
    },
    {
      "id": 10738,
      "enslaved_id": 10738,
      "documented_name": "Guahoo"
    },
    {
      "id": 10739,
      "enslaved_id": 10739,
      "documented_name": "Hoseevah"
    },
    {
      "id": 10740,
      "enslaved_id": 10740,
      "documented_name": "Allubah"
    },
    {
      "id": 10741,
      "enslaved_id": 10741,
      "documented_name": "Hyewoo"
    },
    {
      "id": 10742,
      "enslaved_id": 10742,
      "documented_name": "Mahwoobay"
    },
    {
      "id": 10743,
      "enslaved_id": 10743,
      "documented_name": "Adooahquay"
    },
    {
      "id": 10744,
      "enslaved_id": 10744,
      "documented_name": "Zezah"
    },
    {
      "id": 10745,
      "enslaved_id": 10745,
      "documented_name": "Coyyoo"
    },
    {
      "id": 10746,
      "enslaved_id": 10746,
      "documented_name": "Ahgassay"
    },
    {
      "id": 10747,
      "enslaved_id": 10747,
      "documented_name": "Badahsay"
    },
    {
      "id": 10748,
      "enslaved_id": 10748,
      "documented_name": "Ahgasee"
    },
    {
      "id": 10749,
      "enslaved_id": 10749,
      "documented_name": "Badassay"
    },
    {
      "id": 10750,
      "enslaved_id": 10750,
      "documented_name": "Mannoway"
    },
    {
      "id": 10751,
      "enslaved_id": 10751,
      "documented_name": "Nannequah"
    },
    {
      "id": 10752,
      "enslaved_id": 10752,
      "documented_name": "Ahbasay"
    },
    {
      "id": 10753,
      "enslaved_id": 10753,
      "documented_name": "Kosee"
    },
    {
      "id": 10754,
      "enslaved_id": 10754,
      "documented_name": "Takoyoo"
    },
    {
      "id": 10755,
      "enslaved_id": 10755,
      "documented_name": "Nannah"
    },
    {
      "id": 10756,
      "enslaved_id": 10756,
      "documented_name": "Ahgokay"
    },
    {
      "id": 10757,
      "enslaved_id": 10757,
      "documented_name": "Edeekah"
    },
    {
      "id": 10758,
      "enslaved_id": 10758,
      "documented_name": "Ahgassee"
    },
    {
      "id": 10759,
      "enslaved_id": 10759,
      "documented_name": "Ahgassee"
    },
    {
      "id": 10760,
      "enslaved_id": 10760,
      "documented_name": "Ababee"
    },
    {
      "id": 10761,
      "enslaved_id": 10761,
      "documented_name": "Ababee"
    },
    {
      "id": 10762,
      "enslaved_id": 10762,
      "documented_name": "Daday"
    },
    {
      "id": 10763,
      "enslaved_id": 10763,
      "documented_name": "Daday"
    },
    {
      "id": 10764,
      "enslaved_id": 10764,
      "documented_name": "Sassah"
    },
    {
      "id": 10765,
      "enslaved_id": 10765,
      "documented_name": "Mahhesay"
    },
    {
      "id": 10766,
      "enslaved_id": 10766,
      "documented_name": "Mahhesay"
    },
    {
      "id": 10767,
      "enslaved_id": 10767,
      "documented_name": "Ahgassay"
    },
    {
      "id": 10768,
      "enslaved_id": 10768,
      "documented_name": "Ahgassay"
    },
    {
      "id": 10769,
      "enslaved_id": 10769,
      "documented_name": "Ahdaysobee"
    },
    {
      "id": 10770,
      "enslaved_id": 10770,
      "documented_name": "Ahkimfoo"
    },
    {
      "id": 10771,
      "enslaved_id": 10771,
      "documented_name": "Ahkimfoo"
    },
    {
      "id": 10772,
      "enslaved_id": 10772,
      "documented_name": "Allahbah"
    },
    {
      "id": 10773,
      "enslaved_id": 10773,
      "documented_name": "Hyenah"
    },
    {
      "id": 10774,
      "enslaved_id": 10774,
      "documented_name": "Ahsong"
    },
    {
      "id": 10775,
      "enslaved_id": 10775,
      "documented_name": "Mallahkay"
    },
    {
      "id": 10776,
      "enslaved_id": 10776,
      "documented_name": "Lahway"
    },
    {
      "id": 10777,
      "enslaved_id": 10777,
      "documented_name": "Hyenah"
    },
    {
      "id": 10778,
      "enslaved_id": 10778,
      "documented_name": "Eyahmay"
    },
    {
      "id": 10779,
      "enslaved_id": 10779,
      "documented_name": "Mahbeyay"
    },
    {
      "id": 10780,
      "enslaved_id": 10780,
      "documented_name": "Avetallah"
    },
    {
      "id": 10781,
      "enslaved_id": 10781,
      "documented_name": "Veday"
    },
    {
      "id": 10792,
      "enslaved_id": 10792,
      "documented_name": "Bahwayay"
    },
    {
      "id": 10793,
      "enslaved_id": 10793,
      "documented_name": "Yallayjay"
    },
    {
      "id": 10794,
      "enslaved_id": 10794,
      "documented_name": "Mahesay"
    },
    {
      "id": 10795,
      "enslaved_id": 10795,
      "documented_name": "Dayjee"
    },
    {
      "id": 10796,
      "enslaved_id": 10796,
      "documented_name": "Koyway"
    },
    {
      "id": 10797,
      "enslaved_id": 10797,
      "documented_name": "Ahgoquay"
    },
    {
      "id": 10798,
      "enslaved_id": 10798,
      "documented_name": "Ahballay"
    },
    {
      "id": 10799,
      "enslaved_id": 10799,
      "documented_name": "Guassabee"
    },
    {
      "id": 10800,
      "enslaved_id": 10800,
      "documented_name": "Annahgokay"
    },
    {
      "id": 10801,
      "enslaved_id": 10801,
      "documented_name": "Ahjovahvee"
    },
    {
      "id": 10802,
      "enslaved_id": 10802,
      "documented_name": "Sovay"
    },
    {
      "id": 10803,
      "enslaved_id": 10803,
      "documented_name": "Dachey"
    },
    {
      "id": 10804,
      "enslaved_id": 10804,
      "documented_name": "Modaday"
    },
    {
      "id": 10805,
      "enslaved_id": 10805,
      "documented_name": "Ahbahday"
    },
    {
      "id": 10806,
      "enslaved_id": 10806,
      "documented_name": "Mahhesay"
    },
    {
      "id": 10807,
      "enslaved_id": 10807,
      "documented_name": "Allubah"
    },
    {
      "id": 10808,
      "enslaved_id": 10808,
      "documented_name": "Mahesay"
    },
    {
      "id": 10809,
      "enslaved_id": 10809,
      "documented_name": "Barquay"
    },
    {
      "id": 10810,
      "enslaved_id": 10810,
      "documented_name": "Barquay"
    },
    {
      "id": 10811,
      "enslaved_id": 10811,
      "documented_name": "Allubah"
    },
    {
      "id": 10812,
      "enslaved_id": 10812,
      "documented_name": "Allubah"
    },
    {
      "id": 10813,
      "enslaved_id": 10813,
      "documented_name": "Kachah"
    },
    {
      "id": 10814,
      "enslaved_id": 10814,
      "documented_name": "Kachah"
    },
    {
      "id": 10815,
      "enslaved_id": 10815,
      "documented_name": "Degbay"
    },
    {
      "id": 10816,
      "enslaved_id": 10816,
      "documented_name": "Dadakoo"
    },
    {
      "id": 10817,
      "enslaved_id": 10817,
      "documented_name": "Indaway"
    },
    {
      "id": 10818,
      "enslaved_id": 10818,
      "documented_name": "Ahballay"
    },
    {
      "id": 10819,
      "enslaved_id": 10819,
      "documented_name": "Kohosay"
    },
    {
      "id": 10820,
      "enslaved_id": 10820,
      "documented_name": "Bovee"
    },
    {
      "id": 10821,
      "enslaved_id": 10821,
      "documented_name": "Fodosee"
    },
    {
      "id": 10822,
      "enslaved_id": 10822,
      "documented_name": "Fahdoway"
    },
    {
      "id": 10823,
      "enslaved_id": 10823,
      "documented_name": "Neyoday"
    },
    {
      "id": 10824,
      "enslaved_id": 10824,
      "documented_name": "Koyvee"
    },
    {
      "id": 10825,
      "enslaved_id": 10825,
      "documented_name": "Bokee"
    },
    {
      "id": 10826,
      "enslaved_id": 10826,
      "documented_name": "Dokosee"
    },
    {
      "id": 10827,
      "enslaved_id": 10827,
      "documented_name": "Bovee"
    },
    {
      "id": 10828,
      "enslaved_id": 10828,
      "documented_name": "Bosequay"
    },
    {
      "id": 10829,
      "enslaved_id": 10829,
      "documented_name": "Daygee"
    },
    {
      "id": 10830,
      "enslaved_id": 10830,
      "documented_name": "Dallay"
    },
    {
      "id": 10831,
      "enslaved_id": 10831,
      "documented_name": "Mahsaday"
    },
    {
      "id": 10832,
      "enslaved_id": 10832,
      "documented_name": "Totoe"
    },
    {
      "id": 10833,
      "enslaved_id": 10833,
      "documented_name": "Bojoe"
    },
    {
      "id": 10834,
      "enslaved_id": 10834,
      "documented_name": "Egah"
    },
    {
      "id": 10835,
      "enslaved_id": 10835,
      "documented_name": "Ohooze"
    },
    {
      "id": 10836,
      "enslaved_id": 10836,
      "documented_name": "Aballay"
    },
    {
      "id": 10837,
      "enslaved_id": 10837,
      "documented_name": "Mommo"
    },
    {
      "id": 10838,
      "enslaved_id": 10838,
      "documented_name": "Dajalakotoo"
    }
  ],
  "voyage_crew": {
    "id": 2885,
    "crew_voyage_outset": null,
    "crew_departure_last_port": null,
    "crew_first_landing": null,
    "crew_return_begin": null,
    "crew_end_voyage": null,
    "unspecified_crew": null,
    "crew_died_before_first_trade": null,
    "crew_died_while_ship_african": null,
    "crew_died_middle_passage": null,
    "crew_died_in_americas": null,
    "crew_died_on_return_voyage": null,
    "crew_died_complete_voyage": null,
    "crew_deserted": null,
    "voyage": 2977
  },
  "voyage_ship": {
    "id": 2885,
    "rig_of_vessel": null,
    "imputed_nationality": {
      "id": 1,
      "name": "Portugal / Brazil",
      "value": 6
    },
    "nationality_ship": {
      "id": 2,
      "name": "Portugal",
      "value": 4
    },
    "ton_type": null,
    "vessel_construction_place": null,
    "vessel_construction_region": null,
    "registered_place": null,
    "registered_region": null,
    "ship_name": "NS da Concei\u00e7\u00e3o de Maria",
    "tonnage": null,
    "guns_mounted": null,
    "year_of_construction": null,
    "registered_year": null,
    "tonnage_mod": null,
    "voyage": 2977
  },
  "voyage_slaves_numbers": {
    "id": 2885,
    "slave_deaths_before_africa": null,
    "slave_deaths_between_africa_america": 34,
    "slave_deaths_between_arrival_and_sale": null,
    "num_slaves_intended_first_port": null,
    "num_slaves_intended_second_port": null,
    "num_slaves_carried_first_port": null,
    "num_slaves_carried_second_port": null,
    "num_slaves_carried_third_port": null,
    "total_num_slaves_purchased": null,
    "total_num_slaves_dep_last_slaving_port": 232,
    "total_num_slaves_arr_first_port_embark": 198,
    "num_slaves_disembark_first_place": null,
    "num_slaves_disembark_second_place": null,
    "num_slaves_disembark_third_place": null,
    "imp_total_num_slaves_embarked": 232,
    "imp_total_num_slaves_disembarked": 198,
    "imp_jamaican_cash_price": null,
    "imp_mortality_during_voyage": 34,
    "num_men_embark_first_port_purchase": null,
    "num_women_embark_first_port_purchase": null,
    "num_boy_embark_first_port_purchase": null,
    "num_girl_embark_first_port_purchase": null,
    "num_adult_embark_first_port_purchase": null,
    "num_child_embark_first_port_purchase": null,
    "num_infant_embark_first_port_purchase": null,
    "num_males_embark_first_port_purchase": null,
    "num_females_embark_first_port_purchase": null,
    "num_men_died_middle_passage": null,
    "num_women_died_middle_passage": null,
    "num_boy_died_middle_passage": null,
    "num_girl_died_middle_passage": null,
    "num_adult_died_middle_passage": null,
    "num_child_died_middle_passage": null,
    "num_infant_died_middle_passage": null,
    "num_males_died_middle_passage": null,
    "num_females_died_middle_passage": null,
    "num_men_disembark_first_landing": 45,
    "num_women_disembark_first_landing": 69,
    "num_boy_disembark_first_landing": 59,
    "num_girl_disembark_first_landing": 25,
    "num_adult_disembark_first_landing": null,
    "num_child_disembark_first_landing": null,
    "num_infant_disembark_first_landing": null,
    "num_males_disembark_first_landing": null,
    "num_females_disembark_first_landing": null,
    "num_men_embark_second_port_purchase": null,
    "num_women_embark_second_port_purchase": null,
    "num_boy_embark_second_port_purchase": null,
    "num_girl_embark_second_port_purchase": null,
    "num_adult_embark_second_port_purchase": null,
    "num_child_embark_second_port_purchase": null,
    "num_infant_embark_second_port_purchase": null,
    "num_males_embark_second_port_purchase": null,
    "num_females_embark_second_port_purchase": null,
    "num_men_embark_third_port_purchase": null,
    "num_women_embark_third_port_purchase": null,
    "num_boy_embark_third_port_purchase": null,
    "num_girl_embark_third_port_purchase": null,
    "num_adult_embark_third_port_purchase": null,
    "num_child_embark_third_port_purchase": null,
    "num_infant_embark_third_port_purchase": null,
    "num_males_embark_third_port_purchase": null,
    "num_females_embark_third_port_purchase": null,
    "num_men_disembark_second_landing": null,
    "num_women_disembark_second_landing": null,
    "num_boy_disembark_second_landing": null,
    "num_girl_disembark_second_landing": null,
    "num_adult_disembark_second_landing": null,
    "num_child_disembark_second_landing": null,
    "num_infant_disembark_second_landing": null,
    "num_males_disembark_second_landing": null,
    "num_females_disembark_second_landing": null,
    "imp_num_adult_embarked": null,
    "imp_num_children_embarked": null,
    "imp_num_male_embarked": null,
    "imp_num_female_embarked": null,
    "total_slaves_embarked_age_identified": null,
    "total_slaves_embarked_gender_identified": null,
    "imp_adult_death_middle_passage": null,
    "imp_child_death_middle_passage": null,
    "imp_male_death_middle_passage": null,
    "imp_female_death_middle_passage": null,
    "imp_num_adult_landed": 114,
    "imp_num_child_landed": 84,
    "imp_num_male_landed": 104,
    "imp_num_female_landed": 94,
    "total_slaves_landed_age_identified": 198,
    "total_slaves_landed_gender_identified": 198,
    "total_slaves_dept_or_arr_age_identified": 198,
    "total_slaves_dept_or_arr_gender_identified": 198,
    "imp_slaves_embarked_for_mortality": 232,
    "imp_num_men_total": 45,
    "imp_num_women_total": 69,
    "imp_num_boy_total": 59,
    "imp_num_girl_total": 25,
    "imp_num_adult_total": 114,
    "imp_num_child_total": 84,
    "imp_num_males_total": 104,
    "imp_num_females_total": 94,
    "total_slaves_embarked_age_gender_identified": null,
    "total_slaves_by_age_gender_identified_among_landed": 198,
    "total_slaves_by_age_gender_identified_departure_or_arrival": 198,
    "percentage_boys_among_embarked_slaves": null,
    "child_ratio_among_embarked_slaves": null,
    "percentage_girls_among_embarked_slaves": null,
    "male_ratio_among_embarked_slaves": null,
    "percentage_men_among_embarked_slaves": null,
    "percentage_women_among_embarked_slaves": null,
    "percentage_boys_among_landed_slaves": 0.29798,
    "child_ratio_among_landed_slaves": 0.42424,
    "percentage_girls_among_landed_slaves": 0.12626,
    "male_ratio_among_landed_slaves": 0.52525,
    "percentage_men_among_landed_slaves": 0.22727,
    "percentage_women_among_landed_slaves": 0.34848,
    "percentage_men": 0.22727,
    "percentage_women": 0.34848,
    "percentage_boy": 0.29798,
    "percentage_girl": 0.12626,
    "percentage_male": 0.52525,
    "percentage_child": 0.42424,
    "percentage_adult": 0.57576,
    "percentage_female": 0.47475,
    "imp_mortality_ratio": 0.15,
    "voyage": 2977
  },
  "voyage_outcome": {
    "id": 2885,
    "outcome_owner": {
      "id": 2,
      "name": "Original goal thwarted (human agency)",
      "value": 3
    },
    "outcome_slaves": {
      "id": 5,
      "name": "Slaves disembarked in Old World",
      "value": 3
    },
    "particular_outcome": {
      "id": 19,
      "name": "Court of Mixed Commission, Sierra Leone, condemned",
      "value": 120
    },
    "resistance": null,
    "vessel_captured_outcome": {
      "id": 4,
      "name": "British",
      "value": 3
    },
    "voyage": 2977
  },
  "voyage_groupings": {
    "id": 29,
    "name": "Bahia, post-1825",
    "value": 15
  },
  "cargo": [],
  "african_info": [],
  "linked_voyages": [],
  "voyage_id": 2977,
  "voyage_in_cd_rom": true,
  "last_update": "2023-11-03T22:25:28.372419Z",
  "human_reviewed": false,
  "dataset": 0,
  "comments": null
}